MANIFEST.in
README.md
setup.py
p2sat/__init__.py
p2sat/hist.py
p2sat/plot.py
p2sat/stat.py
p2sat.egg-info/PKG-INFO
p2sat.egg-info/SOURCES.txt
p2sat.egg-info/dependency_links.txt
p2sat.egg-info/top_level.txt
p2sat/datasets/EventLocation.py
p2sat/datasets/FTScalarField.py
p2sat/datasets/PhaseSpace.py
p2sat/datasets/ScalarField.py
p2sat/datasets/_Dataset.py
p2sat/datasets/_EditCommon.py
p2sat/datasets/_EditPhaseSpace.py
p2sat/datasets/_LoadPhaseSpace.py
p2sat/datasets/_MetadataPhaseSpace.py
p2sat/datasets/_ReadPhaseSpace.py
p2sat/datasets/_SavePhaseSpace.py
p2sat/datasets/__init__.py