Metadata-Version: 2.1
Name: p2sat
Version: 2.0.1
Summary: Particle Phase Space Analysis Toolkit
Home-page: https://github.com/lesnat/p2sat
Author: lesnat
License: UNKNOWN
Platform: UNKNOWN
Classifier: Programming Language :: Python
Classifier: Development Status :: 4 - Beta
Classifier: Natural Language :: English
Classifier: License :: OSI Approved :: GNU General Public License v3 (GPLv3)
Classifier: Operating System :: OS Independent
Classifier: Topic :: Scientific/Engineering :: Physics
